motco/__init__.py
motco/cli.py
motco/stats/__init__.py
motco/stats/pls.py
motco/stats/sd.py
motco/stats/snf.py
motco-0.3.0.dist-info/METADATA
motco-0.3.0.dist-info/WHEEL
motco-0.3.0.dist-info/entry_points.txt
motco-0.3.0.dist-info/licenses/LICENSE
motco-0.3.0.dist-info/RECORD
