Metadata-Version: 2.4
Name: motco
Version: 0.3.0
Summary: MOTCO: Multi-omics Trajectory Comparison — latent spaces (PLS, SNF) and group differences
Project-URL: Homepage, https://github.com/
Author: MOTCO Authors
License:                     GNU GENERAL PUBLIC LICENSE
License-File: LICENSE
Classifier: Intended Audience :: Science/Research
Classifier: License :: OSI Approved :: GNU General Public License v3 (GPLv3)
Classifier: Operating System :: OS Independent
Classifier: Programming Language :: Python :: 3
Classifier: Topic :: Scientific/Engineering :: Bio-Informatics
Requires-Python: >=3.11
Requires-Dist: numpy>=1.23
Requires-Dist: pandas-stubs~=2.3.3
Requires-Dist: pandas>=1.5
Requires-Dist: scikit-learn==1.8.0
Requires-Dist: scipy-stubs~=1.16.3
Requires-Dist: scipy>=1.9
Provides-Extra: test
Requires-Dist: pytest-cov>=4.1; extra == 'test'
Requires-Dist: pytest>=7.0; extra == 'test'
